{
 "meta": {
  "variant": "fast",
  "regex_pretok": " ?[^\\W\\d]+| ?\\d+| ?[^\\s\\w]+|\\s+",
  "vocab": 512
 },
 "model": {
  "type": "BPE",
  "vocab": {
   "ДҖ": 0,
   "ДҒ": 1,
   "ДӮ": 2,
   "Дғ": 3,
   "Д„": 4,
   "Д…": 5,
   "ДҶ": 6,
   "ДҮ": 7,
   "ДҲ": 8,
   "Дү": 9,
   "ДҠ": 10,
   "ДӢ": 11,
   "ДҢ": 12,
   "ДҚ": 13,
   "ДҺ": 14,
   "ДҸ": 15,
   "Дҗ": 16,
   "Д‘": 17,
   "Д’": 18,
   "Д“": 19,
   "Д”": 20,
   "Д•": 21,
   "Д–": 22,
   "Д—": 23,
   "Дҳ": 24,
   "Дҷ": 25,
   "Дҡ": 26,
   "Дӣ": 27,
   "Дң": 28,
   "Дқ": 29,
   "Дһ": 30,
   "Дҹ": 31,
   "Д ": 32,
   "!": 33,
   "\"": 34,
   "#": 35,
   "$": 36,
   "%": 37,
   "&": 38,
   "'": 39,
   "(": 40,
   ")": 41,
   "*": 42,
   "+": 43,
   ",": 44,
   "-": 45,
   ".": 46,
   "/": 47,
   "0": 48,
   "1": 49,
   "2": 50,
   "3": 51,
   "4": 52,
   "5": 53,
   "6": 54,
   "7": 55,
   "8": 56,
   "9": 57,
   ":": 58,
   ";": 59,
   "<": 60,
   "=": 61,
   ">": 62,
   "?": 63,
   "@": 64,
   "A": 65,
   "B": 66,
   "C": 67,
   "D": 68,
   "E": 69,
   "F": 70,
   "G": 71,
   "H": 72,
   "I": 73,
   "J": 74,
   "K": 75,
   "L": 76,
   "M": 77,
   "N": 78,
   "O": 79,
   "P": 80,
   "Q": 81,
   "R": 82,
   "S": 83,
   "T": 84,
   "U": 85,
   "V": 86,
   "W": 87,
   "X": 88,
   "Y": 89,
   "Z": 90,
   "[": 91,
   "\\": 92,
   "]": 93,
   "^": 94,
   "_": 95,
   "`": 96,
   "a": 97,
   "b": 98,
   "c": 99,
   "d": 100,
   "e": 101,
   "f": 102,
   "g": 103,
   "h": 104,
   "i": 105,
   "j": 106,
   "k": 107,
   "l": 108,
   "m": 109,
   "n": 110,
   "o": 111,
   "p": 112,
   "q": 113,
   "r": 114,
   "s": 115,
   "t": 116,
   "u": 117,
   "v": 118,
   "w": 119,
   "x": 120,
   "y": 121,
   "z": 122,
   "{": 123,
   "|": 124,
   "}": 125,
   "~": 126,
   "ДЎ": 127,
   "Дў": 128,
   "ДЈ": 129,
   "ДӨ": 130,
   "ДҘ": 131,
   "ДҰ": 132,
   "Д§": 133,
   "ДЁ": 134,
   "Д©": 135,
   "ДӘ": 136,
   "Д«": 137,
   "Д¬": 138,
   "Дӯ": 139,
   "Д®": 140,
   "ДҜ": 141,
   "Д°": 142,
   "Дұ": 143,
   "ДІ": 144,
   "Ді": 145,
   "Дҙ": 146,
   "Дө": 147,
   "Д¶": 148,
   "Д·": 149,
   "Дё": 150,
   "Д№": 151,
   "Дә": 152,
   "Д»": 153,
   "Дј": 154,
   "ДҪ": 155,
   "Дҫ": 156,
   "Дҝ": 157,
   "ЕҖ": 158,
   "ЕҒ": 159,
   "ЕӮ": 160,
   "ВЎ": 161,
   "Вў": 162,
   "ВЈ": 163,
   "ВӨ": 164,
   "ВҘ": 165,
   "ВҰ": 166,
   "В§": 167,
   "ВЁ": 168,
   "В©": 169,
   "ВӘ": 170,
   "В«": 171,
   "В¬": 172,
   "Еғ": 173,
   "В®": 174,
   "ВҜ": 175,
   "В°": 176,
   "Вұ": 177,
   "ВІ": 178,
   "Ві": 179,
   "Вҙ": 180,
   "Вө": 181,
   "В¶": 182,
   "В·": 183,
   "Вё": 184,
   "В№": 185,
   "Вә": 186,
   "В»": 187,
   "Вј": 188,
   "ВҪ": 189,
   "Вҫ": 190,
   "Вҝ": 191,
   "ГҖ": 192,
   "ГҒ": 193,
   "ГӮ": 194,
   "Гғ": 195,
   "Г„": 196,
   "Г…": 197,
   "ГҶ": 198,
   "ГҮ": 199,
   "ГҲ": 200,
   "Гү": 201,
   "ГҠ": 202,
   "ГӢ": 203,
   "ГҢ": 204,
   "ГҚ": 205,
   "ГҺ": 206,
   "ГҸ": 207,
   "Гҗ": 208,
   "Г‘": 209,
   "Г’": 210,
   "Г“": 211,
   "Г”": 212,
   "Г•": 213,
   "Г–": 214,
   "Г—": 215,
   "Гҳ": 216,
   "Гҷ": 217,
   "Гҡ": 218,
   "Гӣ": 219,
   "Гң": 220,
   "Гқ": 221,
   "Гһ": 222,
   "Гҹ": 223,
   "Г ": 224,
   "ГЎ": 225,
   "Гў": 226,
   "ГЈ": 227,
   "ГӨ": 228,
   "ГҘ": 229,
   "ГҰ": 230,
   "Г§": 231,
   "ГЁ": 232,
   "Г©": 233,
   "ГӘ": 234,
   "Г«": 235,
   "Г¬": 236,
   "Гӯ": 237,
   "Г®": 238,
   "ГҜ": 239,
   "Г°": 240,
   "Гұ": 241,
   "ГІ": 242,
   "Гі": 243,
   "Гҙ": 244,
   "Гө": 245,
   "Г¶": 246,
   "Г·": 247,
   "Гё": 248,
   "Г№": 249,
   "Гә": 250,
   "Г»": 251,
   "Гј": 252,
   "ГҪ": 253,
   "Гҫ": 254,
   "Гҝ": 255,
   "ie": 256,
   "Г…ДӨ": 257,
   "Д p": 258,
   "Г„Д»": 259,
   "Д s": 260,
   "ГўДў": 261,
   "Д w": 262,
   "Д n": 263,
   "Д z": 264,
   "Г„Д§": 265,
   "Г…Вј": 266,
   "rz": 267,
   "ДҠДҠ": 268,
   "Д t": 269,
   "ch": 270,
   "Д m": 271,
   "cz": 272,
   "Д d": 273,
   "aГ…ДӨ": 274,
   "ГғВі": 275,
   "iГ„Д»": 276,
   "ГўДўД¶": 277,
   "an": 278,
   "sz": 279,
   "Г…ДҪ": 280,
   "Д o": 281,
   "Д j": 282,
   "Д k": 283,
   "Д i": 284,
   "ow": 285,
   "dz": 286,
   "Д na": 287,
   "Г„Д©": 288,
   "Д b": 289,
   "st": 290,
   "ra": 291,
   "ro": 292,
   "Д po": 293,
   "Д Д ": 294,
   "Д nie": 295,
   "go": 296,
   "rze": 297,
   "Д siГ„Д»": 298,
   "li": 299,
   "ak": 300,
   "le": 301,
   "ci": 302,
   "nie": 303,
   "ni": 304,
   "ГўДўВҰ": 305,
   "Г…Вјe": 306,
   "Д ГўДўД¶": 307,
   "Д za": 308,
   "Д do": 309,
   "ki": 310,
   "Д je": 311,
   "ar": 312,
   "em": 313,
   "rzy": 314,
   "am": 315,
   "Д a": 316,
   "wi": 317,
   "na": 318,
   "Г…ДӨo": 319,
   "Г…ДӨa": 320,
   "Д pan": 321,
   "ym": 322,
   "Д g": 323,
   "Д c": 324,
   "ka": 325,
   "Д u": 326,
   "ko": 327,
   "Д Д Д Д ": 328,
   "Д W": 329,
   "ny": 330,
   "ej": 331,
   "Д Г…Вјe": 332,
   "dzi": 333,
   "ГғВіw": 334,
   "ku": 335,
   "Д wy": 336,
   "la": 337,
   "czy": 338,
   "Д to": 339,
   "cie": 340,
   "dy": 341,
   "dzie": 342,
   "Г„Д§c": 343,
   "Д od": 344,
   "kie": 345,
   "aj": 346,
   "Д st": 347,
   "Д prze": 348,
   "Д ch": 349,
   "po": 350,
   "ego": 351,
   "Д jak": 352,
   "by": 353,
   "wo": 354,
   "Д by": 355,
   "ry": 356,
   "wa": 357,
   "szy": 358,
   "ski": 359,
   "Д ko": 360,
   "tГғВі": 361,
   "Д mi": 362,
   "Д P": 363,
   "no": 364,
   "at": 365,
   "Г…ДҪci": 366,
   "si": 367,
   "Д cz": 368,
   "ru": 369,
   "Д przy": 370,
   "Д sz": 371,
   "bie": 372,
   "Д ro": 373,
   "re": 374,
   "Д S": 375,
   "nГ„Д§": 376,
   "Г…ДҰ": 377,
   "Д ktГғВі": 378,
   "ad": 379,
   "Д mo": 380,
   "aГ„Д©": 381,
   "Д ni": 382,
   "owie": 383,
   "Д ty": 384,
   "je": 385,
   "Г…ДӨy": 386,
   "Д tak": 387,
   "aГ…ДӨa": 388,
   "mie": 389,
   "Д N": 390,
   "Д A": 391,
   "mi": 392,
   "Д M": 393,
   "Д go": 394,
   "ta": 395,
   "Д co": 396,
   "ne": 397,
   "cze": 398,
   "wie": 399,
   "ce": 400,
   "Д C": 401,
   "Д Д Д Д Д Д Д Д ": 402,
   "bi": 403,
   "oku": 404,
   "ДҠДҠДҠ": 405,
   "cy": 406,
   "okul": 407,
   "Д wie": 408,
   "raz": 409,
   "uГ…Вј": 410,
   "Д dz": 411,
   "Д T": 412,
   "Г…ДҪГ„Д©": 413,
   "Д te": 414,
   "lu": 415,
   "te": 416,
   "ty": 417,
   "Д Г…ДҪ": 418,
   "Д mu": 419,
   "Д B": 420,
   "to": 421,
   "ani": 422,
   "Д K": 423,
   "sze": 424,
   "ba": 425,
   "Д jest": 426,
   "Д Z": 427,
   "Г…Вјy": 428,
   "as": 429,
   "Д roz": 430,
   "Д Wokul": 431,
   "Д pod": 432,
   "Д wi": 433,
   "er": 434,
   "ami": 435,
   "Д J": 436,
   "Г…ДӨu": 437,
   "Г…Вә": 438,
   "my": 439,
   "skie": 440,
   "Д mГғВі": 441,
   "Д I": 442,
   "?ГўДўВҰ": 443,
   "Д sp": 444,
   "da": 445,
   "nia": 446,
   "Д ale": 447,
   "rГ„Д»": 448,
   "bo": 449,
   "!ГўДўВҰ": 450,
   "cho": 451,
   "Д wo": 452,
   "rГғВі": 453,
   "Д mnie": 454,
   "waГ…ДӨ": 455,
   "pie": 456,
   "wy": 457,
   "owa": 458,
   "Д O": 459,
   "tu": 460,
   "pi": 461,
   "et": 462,
   "Д spo": 463,
   "Д rze": 464,
   "owi": 465,
   "Д bo": 466,
   "Д juГ…Вј": 467,
   "ach": 468,
   "nГ„Д»": 469,
   "Д h": 470,
   "Д Wokulski": 471,
   "Д jed": 472,
   "Д ci": 473,
   "za": 474,
   "mo": 475,
   "mu": 476,
   "gi": 477,
   "Д R": 478,
   "ГўДўЕҖ": 479,
   "ГўДўДҝ": 480,
   "en": 481,
   "al": 482,
   "nym": 483,
   "lko": 484,
   "Д ja": 485,
   "nГ„Д§Г…ДӨ": 486,
   "Д Nie": 487,
   "Д D": 488,
   "Д ob": 489,
   "zy": 490,
   "ca": 491,
   "Д f": 492,
   "aГ…ДӨy": 493,
   "iГ„Д»c": 494,
   "Д pani": 495,
   "Г„Д§d": 496,
   "cki": 497,
   "Д lu": 498,
   "Д ku": 499,
   "ajГ„Д§c": 500,
   "Д mГғВіwi": 501,
   "Д wszy": 502,
   "Д sk": 503,
   "anie": 504,
   "Д ze": 505,
   "Д my": 506,
   "ja": 507,
   "be": 508,
   "ze": 509,
   "Д tylko": 510,
   "Д ma": 511
  },
  "merges": [
   "i e",
   "Г… ДӨ",
   "Д  p",
   "Г„ Д»",
   "Д  s",
   "Гў Дў",
   "Д  w",
   "Д  n",
   "Д  z",
   "Г„ Д§",
   "Г… Вј",
   "r z",
   "ДҠ ДҠ",
   "Д  t",
   "c h",
   "Д  m",
   "c z",
   "Д  d",
   "a Г…ДӨ",
   "Гғ Ві",
   "i Г„Д»",
   "ГўДў Д¶",
   "a n",
   "s z",
   "Г… ДҪ",
   "Д  o",
   "Д  j",
   "Д  k",
   "Д  i",
   "o w",
   "d z",
   "Д n a",
   "Г„ Д©",
   "Д  b",
   "s t",
   "r a",
   "r o",
   "Д p o",
   "Д  Д ",
   "Д n ie",
   "g o",
   "rz e",
   "Д s iГ„Д»",
   "l i",
   "a k",
   "l e",
   "c i",
   "n ie",
   "n i",
   "ГўДў ВҰ",
   "Г…Вј e",
   "Д  ГўДўД¶",
   "Д z a",
   "Д d o",
   "k i",
   "Д j e",
   "a r",
   "e m",
   "rz y",
   "a m",
   "Д  a",
   "w i",
   "n a",
   "Г…ДӨ o",
   "Г…ДӨ a",
   "Д p an",
   "y m",
   "Д  g",
   "Д  c",
   "k a",
   "Д  u",
   "k o",
   "Д Д  Д Д ",
   "Д  W",
   "n y",
   "e j",
   "Д  Г…Вјe",
   "dz i",
   "ГғВі w",
   "k u",
   "Д w y",
   "l a",
   "cz y",
   "Д t o",
   "c ie",
   "d y",
   "dz ie",
   "Г„Д§ c",
   "Д o d",
   "k ie",
   "a j",
   "Д s t",
   "Д p rze",
   "Д  ch",
   "p o",
   "e go",
   "Д j ak",
   "b y",
   "w o",
   "Д b y",
   "r y",
   "w a",
   "sz y",
   "s ki",
   "Д k o",
   "t ГғВі",
   "Д m i",
   "Д  P",
   "n o",
   "a t",
   "Г…ДҪ ci",
   "s i",
   "Д  cz",
   "r u",
   "Д p rzy",
   "Д s z",
   "b ie",
   "Д  ro",
   "r e",
   "Д  S",
   "n Г„Д§",
   "Г… ДҰ",
   "Д k tГғВі",
   "a d",
   "Д m o",
   "a Г„Д©",
   "Д n i",
   "ow ie",
   "Д t y",
   "j e",
   "Г…ДӨ y",
   "Д t ak",
   "aГ…ДӨ a",
   "m ie",
   "Д  N",
   "Д  A",
   "m i",
   "Д  M",
   "Д  go",
   "t a",
   "Д c o",
   "n e",
   "cz e",
   "w ie",
   "c e",
   "Д  C",
   "Д Д Д Д  Д Д Д Д ",
   "b i",
   "o ku",
   "ДҠДҠ ДҠ",
   "c y",
   "oku l",
   "Д w ie",
   "ra z",
   "u Г…Вј",
   "Д d z",
   "Д  T",
   "Г…ДҪ Г„Д©",
   "Д t e",
   "l u",
   "t e",
   "t y",
   "Д  Г…ДҪ",
   "Д m u",
   "Д  B",
   "t o",
   "an i",
   "Д  K",
   "sz e",
   "b a",
   "Д je st",
   "Д  Z",
   "Г…Вј y",
   "a s",
   "Д ro z",
   "Д W okul",
   "Д po d",
   "Д w i",
   "e r",
   "am i",
   "Д  J",
   "Г…ДӨ u",
   "Г… Вә",
   "m y",
   "s kie",
   "Д m ГғВі",
   "Д  I",
   "? ГўДўВҰ",
   "Д s p",
   "d a",
   "ni a",
   "Д a le",
   "r Г„Д»",
   "b o",
   "! ГўДўВҰ",
   "ch o",
   "Д w o",
   "r ГғВі",
   "Д m nie",
   "w aГ…ДӨ",
   "p ie",
   "w y",
   "ow a",
   "Д  O",
   "t u",
   "p i",
   "e t",
   "Д s po",
   "Д  rze",
   "ow i",
   "Д b o",
   "Д j uГ…Вј",
   "a ch",
   "n Г„Д»",
   "Д  h",
   "Д Wokul ski",
   "Д je d",
   "Д  ci",
   "z a",
   "m o",
   "m u",
   "g i",
   "Д  R",
   "ГўДў ЕҖ",
   "ГўДў Дҝ",
   "e n",
   "a l",
   "n ym",
   "l ko",
   "Д j a",
   "nГ„Д§ Г…ДӨ",
   "Д N ie",
   "Д  D",
   "Д o b",
   "z y",
   "c a",
   "Д  f",
   "aГ…ДӨ y",
   "iГ„Д» c",
   "Д pan i",
   "Г„Д§ d",
   "c ki",
   "Д  lu",
   "Д k u",
   "aj Г„Д§c",
   "Д mГғВі wi",
   "Д w szy",
   "Д s k",
   "an ie",
   "Д z e",
   "Д m y",
   "j a",
   "b e",
   "z e",
   "Д ty lko",
   "Д m a"
  ]
 }
}